{
    "type": "object",
    "questionList": {
        "一": [87.97, 176.03, 274.29, 357.48, 437.01],
        "二": [546.69, 651.31, 753.45, 855.06, 952.57, 1046.77],
        "三": [1228.24, 1309.76, 1405.041, 1488, 1587.03],
        "四a": [1701.8, 1735.19, 1766.96, 1800.418, 1831.418, 1866.807],
        "四b": [1897.83, 1931.66, 1964.18, 1997.58, 2030.11, 2062.64],
        "五": [2129.51, 2254.128, 2390.47]
    },
    "data": [
        { "st": 4.22, "et": 6.64, "text": "これから音を聞いてください。" },
        {
            "st": 7.9,
            "et": 11.26,
            "text": " 音がよく聞こえないときは手を挙げてください。"
        },
        { "st": 14.38, "et": 16.54, "text": "天気がいいから散歩しましょう。" },
        { "st": 17.68, "et": 19.76, "text": " 天気がいいから散歩しましょう。" },
        { "st": 20.86, "et": 22.9, "text": "天気がいいから散歩しましょう。" },
        { "st": 24.02, "et": 26.1, "text": " 天気がいいから散歩しましょう。" },
        {
            "st": 34.51,
            "et": 37.43,
            "text": "問題用紙にメモを取ってもかまいません。"
        },
        { "st": 39.15, "et": 40.81, "text": " 問題用紙を開けてください。" },
        {
            "st": 42.87,
            "et": 46.41,
            "text": "問題用紙のページがないときは手を挙げてください。"
        },
        {
            "st": 48.25,
            "et": 51.65,
            "text": " 問題がよく見えないときも手を挙げてください。"
        },
        { "st": 52.81, "et": 53.85, "text": "いつでもいいです。" },
        {
            "st": 61.06,
            "et": 66.74,
            "text": "問題1 問題1ではまず質問を聞いてください。"
        },
        {
            "st": 68.4,
            "et": 76.72,
            "text": "それから話を聞いて問題用紙の1から4の中から最も良いものを1つ選んでください。"
        },
        { "st": 79.78, "et": 81.46, "text": "では始めます。" },
        {
            "st": 87.97,
            "et": 93.83,
            "text": "1番 大学で男の人と女の人が話しています。"
        },
        { "st": 95.03, "et": 98.07, "text": "女の人はこの後何をしますか?" },
        { "st": 99.65, "et": 101.83, "text": "青木さん何見てるの?" },
        { "st": 102.27, "et": 103.49, "text": "ああ、これ。" },
        {
            "st": 104.35,
            "et": 106.27,
            "text": "アパートの情報が載ってる雑誌。"
        },
        { "st": 107.13, "et": 109.03, "text": "今アパートを探してるんだ。" },
        {
            "st": 110.47,
            "et": 114.39,
            "text": "そういえば山田君って最近引っ越ししたんだよね。"
        },
        { "st": 115.17, "et": 116.61, "text": "どうやって部屋探したの?" },
        { "st": 117.21000000000001, "et": 117.97, "text": "そうだな。" },
        {
            "st": 118.71,
            "et": 120.67,
            "text": "もちろん不動産屋にも行ったんだけど、"
        },
        {
            "st": 121.53,
            "et": 128.13,
            "text": "不動産屋に行く前に家賃とか日当たりとか気になる条件をノートに書き出して整理してみたよ。"
        },
        { "st": 128.75, "et": 130.65, "text": "それは一応やったんだけどね。" },
        { "st": 130.85, "et": 131.41, "text": "そうなんだ。" },
        {
            "st": 132.75,
            "et": 135.97,
            "text": "あと住みたい町に実際に行ってみるといいよ。"
        },
        {
            "st": 136.71,
            "et": 141.23,
            "text": "運が良ければ歩いているうちに良さそうなアパートが見つかるかもしれないし。"
        },
        { "st": 142.31, "et": 144.05, "text": "住みたい町はもう決まってるの?" },
        { "st": 144.57, "et": 146.65, "text": "うん、一応候補あるの。" },
        { "st": 147.61, "et": 149.25, "text": "今日はもう授業ないし、" },
        {
            "st": 149.71,
            "et": 150.99,
            "text": "これからちょっと行ってみよう。"
        },
        { "st": 156.83, "et": 160.55, "text": "女の人はこの後何をしますか?" },
        {
            "st": 176.03,
            "et": 180.17,
            "text": "2番女の人が友達と話しています。"
        },
        {
            "st": 181.13,
            "et": 185.75,
            "text": "女の人は地震に備えて何をしておけばいいですか?"
        },
        { "st": 187.65, "et": 188.83, "text": "この間の地震、" },
        {
            "st": 189.23000000000002,
            "et": 190.87,
            "text": "かなり揺れて怖かったね。"
        },
        {
            "st": 191.85,
            "et": 195.89,
            "text": "地震が来た時のために何かしとかなくちゃって思ってるんだけど、"
        },
        {
            "st": 196.75,
            "et": 199.05,
            "text": "実際にどういうことをすればいいのかな?"
        },
        {
            "st": 199.71,
            "et": 203.01,
            "text": "やっぱり怖いのは家具が倒れることだから、"
        },
        {
            "st": 203.81,
            "et": 207.87,
            "text": "本棚とか背の高い家具があったら壁に固定した方がいいよ。"
        },
        {
            "st": 208.43,
            "et": 214.41,
            "text": "あー、でもうちの家具みんな背が低いからそれは大丈夫かな。"
        },
        { "st": 214.70999999999998, "et": 215.29, "text": "そっか。" },
        {
            "st": 216.21,
            "et": 219.07,
            "text": "あ、それから避難用のセットはある?"
        },
        {
            "st": 219.97,
            "et": 226.33,
            "text": "すぐ持ち出せるように水や食べ物を入れた袋は必ず用意しておいた方がいいってテレビで言ってたよ。"
        },
        { "st": 226.43, "et": 228.49, "text": "あ、それは持ってないな。" },
        { "st": 229.19, "et": 230.17, "text": "どこで売ってるの?" },
        { "st": 230.61, "et": 231.75, "text": "デパートとかにあるよ。" },
        { "st": 232.17, "et": 233.07, "text": "じゃあ探してみる。" },
        {
            "st": 233.71,
            "et": 239.17,
            "text": "あとはうちの人と話し合って家族の避難場所を決めておいた方がいいよ。"
        },
        {
            "st": 239.17,
            "et": 245.45,
            "text": "あ、でもう今家族はみんな海外に住んでるからそれは関係ないかな。"
        },
        { "st": 246.99, "et": 247.73, "text": "いろいろありがとう。" },
        {
            "st": 253.69,
            "et": 258.39,
            "text": "女の人は地震に備えて何をしておけばいいですか?"
        },
        {
            "st": 274.29,
            "et": 279.79,
            "text": "3番電話で病院の診察の予約をしようと思っています。"
        },
        {
            "st": 281.09,
            "et": 286.41,
            "text": "今日の午後の診察を予約するにはどの番号を押せばいいですか?"
        },
        {
            "st": 288.45,
            "et": 291.07,
            "text": "山川病院自動予約システムです。"
        },
        {
            "st": 292.09,
            "et": 296.95,
            "text": "最初にご希望のお日にちを4桁の番号でご入力ください。"
        },
        { "st": 298.55, "et": 302.91, "text": "5月3日なら0503となります。" },
        {
            "st": 304.19000000000005,
            "et": 312.95,
            "text": "ただし本日の診察をご希望の方は日にちではなく0001とご入力ください。"
        },
        {
            "st": 314.85,
            "et": 319.33,
            "text": "次に午前中をご希望なら続けて01。"
        },
        { "st": 320.7900000000001, "et": 322.29, "text": "午後なら02。" },
        {
            "st": 323.87,
            "et": 328.27,
            "text": "特にご希望のない方は09と入力してください。"
        },
        {
            "st": 336.41,
            "et": 341.65,
            "text": "今日の午後の診察を予約するにはどの番号を押せばいいですか?"
        },
        {
            "st": 357.48,
            "et": 363.86,
            "text": "4番会社で女の人が男の人と電話で話しています。"
        },
        {
            "st": 365.41999999999996,
            "et": 370.42,
            "text": "女の人は同僚の田中さんにどんなメモを書きますか?"
        },
        {
            "st": 372.32000000000005,
            "et": 373.96,
            "text": "はい、富士出版です。"
        },
        { "st": 374.38, "et": 375.62, "text": "お世話になっております。" },
        {
            "st": 376.15999999999997,
            "et": 378.04,
            "text": "桜印刷の山川ですが、"
        },
        {
            "st": 378.35999999999996,
            "et": 379.68,
            "text": "田中さんはいらっしゃいますか?"
        },
        { "st": 380.16, "et": 381.32, "text": "お世話になっております。" },
        {
            "st": 382.14,
            "et": 384.68,
            "text": "あいにく田中は席を外しておりまして、"
        },
        {
            "st": 385.58,
            "et": 389.48,
            "text": "2時からミーティングがあるのでその前には戻る予定ですが。"
        },
        { "st": 389.78, "et": 390.4, "text": "そうですか。" },
        {
            "st": 391.34,
            "et": 395.9,
            "text": "実は先ほど私が留守の間田中さんからお電話をいただいたようで、"
        },
        {
            "st": 396.58,
            "et": 398.98,
            "text": "明日の会議の件だとお伝言があったのですが。"
        },
        { "st": 399.48000000000013, "et": 400.14, "text": "そうですか。" },
        { "st": 400.9, "et": 402.86, "text": "では田中が戻り次第、" },
        {
            "st": 403.26,
            "et": 407.12,
            "text": "山川さんに折り返しお電話差し上げるよう伝えましょうか。"
        },
        { "st": 407.38, "et": 408.42, "text": "お願いできますか。" },
        { "st": 408.76, "et": 410.1, "text": "はい、かしこまりました。" },
        {
            "st": 416.08,
            "et": 421.44,
            "text": "女の人は同僚の田中さんにどんなメモを書きますか?"
        },
        {
            "st": 437.01,
            "et": 442.93,
            "text": "5番大学で男の学生と先生が話しています。"
        },
        { "st": 444.21, "et": 445.39, "text": " 学生はこの後、" },
        {
            "st": 446.03,
            "et": 448.51,
            "text": "まず何をしなければなりませんか?"
        },
        {
            "st": 450.43,
            "et": 454.31,
            "text": "先生、先日お渡しした論文の件なんですが、"
        },
        { "st": 455.07, "et": 456.77, "text": "見ていただけましたでしょうか?" },
        { "st": 457.05, "et": 459.11, "text": "うん、よく書けてましたよ。" },
        {
            "st": 460.05,
            "et": 462.11,
            "text": "いくつか字の間違いがあったのと、"
        },
        {
            "st": 462.48999999999995,
            "et": 466.49,
            "text": "参考文献の書き方にちょっと気になる点がありましたけどね。"
        },
        { "st": 466.69000000000005, "et": 467.77, "text": "あ、はい。" },
        { "st": 468.31, "et": 471.81, "text": "あとは、このグラフの値、" },
        { "st": 472.39, "et": 473.65, "text": "これで正しいですか?" },
        { "st": 474.35, "et": 477.51, "text": "えっと...あ、" },
        { "st": 477.93, "et": 478.53, "text": "すみません。" },
        { "st": 479.19, "et": 480.47, "text": "直したはずだったんですが、" },
        { "st": 480.89, "et": 482.23, "text": "古い方のデータです。" },
        { "st": 482.65, "et": 483.73, "text": "大事なところだから、" },
        { "st": 484.31, "et": 485.65, "text": "まずはここだけ直して、" },
        { "st": 486.07, "et": 487.01, "text": "すぐ見せてください。" },
        { "st": 487.37, "et": 488.51, "text": "はい、わかりました。" },
        { "st": 489.15, "et": 490.17, "text": "あ、それから、" },
        {
            "st": 490.69,
            "et": 493.23,
            "text": "今年から提出部数が3部になったから、"
        },
        { "st": 493.81, "et": 494.57, "text": "忘れないでね。" },
        { "st": 500.67, "et": 501.97, "text": "学生はこの後、" },
        {
            "st": 502.61,
            "et": 505.21,
            "text": "まず何をしなければなりませんか?"
        },
        { "st": 512.48, "et": 513.42, "text": "問題2。" },
        {
            "st": 514.28,
            "et": 517.92,
            "text": "問題2では、まず質問を聞いてください。"
        },
        {
            "st": 519.5,
            "et": 522.98,
            "text": "その後、問題用紙の選択肢を読んでください。"
        },
        { "st": 524.24, "et": 525.4, "text": "読む時間があります。" },
        { "st": 527, "et": 528.68, "text": "それから話を聞いて、" },
        { "st": 529.24, "et": 531.84, "text": "問題用紙の1から4の中から、" },
        {
            "st": 532.3199999999999,
            "et": 535.02,
            "text": "最も良いものを1つ選んでください。"
        },
        { "st": 537.88, "et": 539.64, "text": "では、始めます。" },
        { "st": 546.69, "et": 547.29, "text": "1番。" },
        {
            "st": 548.29,
            "et": 551.79,
            "text": "家で息子と母親が話をしています。"
        },
        {
            "st": 552.83,
            "et": 556.23,
            "text": "息子は明日、どこに行くと言っていますか?"
        },
        {
            "st": 580.13,
            "et": 583.05,
            "text": "明日、午前中から出かけるからね。"
        },
        {
            "st": 583.47,
            "et": 586.29,
            "text": "ああ、友達と釣りに行くんだったよね。"
        },
        { "st": 586.91, "et": 587.27, "text": "うん。" },
        { "st": 588.15, "et": 591.09, "text": "それが、その友達が先週、" },
        { "st": 591.29, "et": 592.23, "text": "自転車で転んで、" },
        { "st": 592.89, "et": 594.07, "text": "足怪我しちゃってね。" },
        { "st": 594.93, "et": 595.85, "text": "今、入院してるんだ。" },
        {
            "st": 596.51,
            "et": 598.77,
            "text": "じゃあ、お見舞いに行ってあげなくちゃ。"
        },
        { "st": 599.31, "et": 599.65, "text": "ううん。" },
        {
            "st": 600.57,
            "et": 602.97,
            "text": "明日はね、あいつのアパートに行くんだ。"
        },
        { "st": 603.81, "et": 604.05, "text": "え?" },
        {
            "st": 604.9300000000001,
            "et": 607.31,
            "text": "その時の自転車が修理に出してあってね。"
        },
        {
            "st": 608.31,
            "et": 611.11,
            "text": "治ったから、明日配達してもらうことになったんだ。"
        },
        { "st": 611.63, "et": 611.95, "text": "そう?" },
        {
            "st": 612.75,
            "et": 614.35,
            "text": "店に取りに行ってもいいんだけど、"
        },
        {
            "st": 615.19,
            "et": 617.45,
            "text": "俺が乗って、また壊しちゃってもまずいし。"
        },
        { "st": 617.79, "et": 618.69, "text": "それはそうね。" },
        { "st": 619.31, "et": 620.41, "text": "あいつ一人暮らしだから、" },
        {
            "st": 621.15,
            "et": 622.65,
            "text": "代わりに俺が受け取るってわけ。"
        },
        { "st": 623.13, "et": 623.83, "text": "そうなの。" },
        { "st": 624.67, "et": 625.95, "text": "それはご苦労様ね。" },
        {
            "st": 632.01,
            "et": 635.81,
            "text": "息子は明日、どこに行くと言っていますか?"
        },
        {
            "st": 651.41,
            "et": 656.19,
            "text": "2番女の学生と男の学生が話しています。"
        },
        {
            "st": 657.8100000000001,
            "et": 662.21,
            "text": "男の学生が就職する会社を選んだ理由は何ですか?"
        },
        { "st": 686.24, "et": 687.94, "text": "就職決まったんだって?" },
        {
            "st": 688.78,
            "et": 690.98,
            "text": "先輩に紹介してもらったあの会社?"
        },
        {
            "st": 690.98,
            "et": 694.62,
            "text": "うーん、あそこも採用の連絡はもらったんだけど、"
        },
        {
            "st": 695.54,
            "et": 697.82,
            "text": "決めたのは先生に紹介してもらった会社。"
        },
        {
            "st": 698.64,
            "et": 701.5,
            "text": "そこだと大学で勉強したことを活かせそうなんだ。"
        },
        { "st": 701.92, "et": 703.78, "text": "そう、それは良かったね。" },
        { "st": 704.48, "et": 705.8, "text": "仕事はハードだし、" },
        {
            "st": 706.4,
            "et": 708.16,
            "text": "帰りも遅くなるらしいんだけどね。"
        },
        {
            "st": 708.5999999999999,
            "et": 710.86,
            "text": "でも残業代つくんでしょ?"
        },
        { "st": 711.34, "et": 712.44, "text": "まあ、一応ね。" },
        { "st": 713.58, "et": 715.64, "text": "それより会社が遠くて、" },
        {
            "st": 715.9599999999999,
            "et": 717.42,
            "text": "引っ越しもしなくちゃいけないんだ。"
        },
        { "st": 718.14, "et": 719.06, "text": "それがちょっとね。" },
        {
            "st": 719.6800000000001,
            "et": 722.24,
            "text": "でもまあ、決まって良かったじゃない。"
        },
        { "st": 722.78, "et": 723.28, "text": "そうだね。" },
        { "st": 724.16, "et": 725.56, "text": "給料はそんなでもないけど、" },
        { "st": 726.4, "et": 728.02, "text": "頑張ってみるよ。" },
        {
            "st": 733.0600000000001,
            "et": 737.82,
            "text": "男の学生が就職する会社を選んだ理由は何ですか?"
        },
        {
            "st": 753.45,
            "et": 759.45,
            "text": "3番大学で男の学生と女の学生が話しています。"
        },
        {
            "st": 760.43,
            "et": 764.61,
            "text": "男の学生はどうして怒っていますか?"
        },
        { "st": 787.38, "et": 788.24, "text": "おはよう。" },
        { "st": 788.62, "et": 789.2, "text": "おはよう。" },
        {
            "st": 789.94,
            "et": 792.92,
            "text": "あれ、今日授業2時間目からだっけ?"
        },
        { "st": 793.56, "et": 796.2, "text": "うん、1時間目からだよ。" },
        { "st": 796.68, "et": 797.92, "text": "ねえ、聞いてよ。" },
        {
            "st": 799.02,
            "et": 801.78,
            "text": "今日、学校に来る時の電車のことなんだけど。"
        },
        { "st": 802.1, "et": 803.3, "text": "うん、どうしたの?" },
        { "st": 804.14, "et": 805.92, "text": "今朝、事故があったみたいで、" },
        {
            "st": 806.1999999999999,
            "et": 807.72,
            "text": "いつもより電車が混んでてね。"
        },
        { "st": 807.9200000000001, "et": 808.42, "text": "うん。" },
        {
            "st": 809.18,
            "et": 810.94,
            "text": "それはしょうがないと思うんだけど、"
        },
        { "st": 811.82, "et": 813.26, "text": "電車を降りようとしても、" },
        {
            "st": 813.58,
            "et": 816.38,
            "text": "ドアの近くにいる人がなかなか動いてくれなくて。"
        },
        { "st": 816.74, "et": 817.48, "text": "へえ。" },
        { "st": 817.9, "et": 819.64, "text": "それで、すみません、" },
        { "st": 819.86, "et": 821.14, "text": "降りますって言ったんだけど、" },
        { "st": 821.88, "et": 823.04, "text": "結局降りられなくて。" },
        { "st": 823.48, "et": 825.72, "text": "へえ、大変だったね。" },
        { "st": 826.3, "et": 827.92, "text": "次の駅まで行っちゃったんだよ。" },
        { "st": 828.78, "et": 829.5, "text": "そうなんだ。" },
        {
            "st": 835.96,
            "et": 839.86,
            "text": "男の学生はどうして怒っていますか?"
        },
        {
            "st": 855.06,
            "et": 860.26,
            "text": "4番会社で女の人と男の人が話しています。"
        },
        {
            "st": 861.66,
            "et": 865.84,
            "text": "男の人はどうして禁煙することにしたと言っていますか?"
        },
        { "st": 889.699, "et": 891.7, "text": "あれ?タバコをやめたの?" },
        { "st": 892.14, "et": 892.5, "text": "うん。" },
        { "st": 893.26, "et": 894.18, "text": "禁煙したんだ。" },
        { "st": 894.46, "et": 895.32, "text": "へえ。" },
        {
            "st": 896.14,
            "et": 898.96,
            "text": "前は医者に吸うなって言われても吸ってたのに。"
        },
        { "st": 899.24, "et": 899.52, "text": "うん。" },
        { "st": 900.18, "et": 901.64, "text": "実は結婚してからね、" },
        {
            "st": 901.88,
            "et": 903.86,
            "text": "家族への影響も考えるようになってね。"
        },
        { "st": 904.42, "et": 904.78, "text": "そう。" },
        {
            "st": 905.66,
            "et": 908.54,
            "text": "確かに、タバコは吸う人だけじゃなくて、"
        },
        {
            "st": 908.86,
            "et": 911.36,
            "text": "周囲の人にも悪いって言われてるよね。"
        },
        { "st": 911.8, "et": 912.16, "text": "うん。" },
        {
            "st": 913.2,
            "et": 915.48,
            "text": "はじめは難しいかなって思ってたんだけど、"
        },
        {
            "st": 916.16,
            "et": 918.38,
            "text": "駅とか吸えない場所も増えてきてるし、"
        },
        { "st": 919.2, "et": 920.5, "text": "もう結構続いてるんだ。" },
        { "st": 920.8999999999997, "et": 921.5599999999998, "text": "そう。" },
        {
            "st": 922.36,
            "et": 924.56,
            "text": "最近タバコも値上がりしてるし、"
        },
        { "st": 925.12, "et": 926.42, "text": "ちょうどいい機会かもね。" },
        {
            "st": 932.36,
            "et": 936.76,
            "text": "男の人はどうして禁煙することにしたと言っていますか?"
        },
        {
            "st": 952.6700000000001,
            "et": 956.57,
            "text": "5番留守番電話のメッセージを聞いています。"
        },
        {
            "st": 957.77,
            "et": 961.83,
            "text": "女の人はどうして勉強会に参加できませんか?"
        },
        { "st": 988.49, "et": 989.67, "text": "あ、木村です。" },
        {
            "st": 990.53,
            "et": 992.63,
            "text": "明日の勉強会のことなんだけど、"
        },
        {
            "st": 993.45,
            "et": 996.07,
            "text": "悪いけど急に行けなくなっちゃったの。"
        },
        {
            "st": 997.01,
            "et": 1001.03,
            "text": "風邪をひいたからバイトを変わってほしいって頼まれちゃって、"
        },
        {
            "st": 1001.97,
            "et": 1006.87,
            "text": "私もこの前旅行した時変わってもらったから断りにくくて、"
        },
        { "st": 1007.73, "et": 1008.59, "text": "急でごめんね。" },
        {
            "st": 1009.6899999999999,
            "et": 1012.03,
            "text": "あと借りてた本返すの、"
        },
        {
            "st": 1012.21,
            "et": 1014.09,
            "text": "今度大学で会った時でいいかな。"
        },
        { "st": 1015.29, "et": 1016.75, "text": "また後で電話するね。" },
        { "st": 1017.35, "et": 1017.61, "text": "じゃあ。" },
        {
            "st": 1026.76,
            "et": 1031.16,
            "text": "女の人はどうして勉強会に参加できませんか?"
        },
        {
            "st": 1046.67,
            "et": 1051.87,
            "text": "6番会社で男の人と女の人が話しています。"
        },
        {
            "st": 1053.41,
            "et": 1059.39,
            "text": "女の人はジョギングを始めて一番良かったことは何だと言っていますか?"
        },
        {
            "st": 1083.3100000000002,
            "et": 1086.43,
            "text": "そういえば先輩ジョギング始めたそうですね。"
        },
        { "st": 1087.0700000000002, "et": 1087.83, "text": "そうなの。" },
        {
            "st": 1088.43,
            "et": 1093.81,
            "text": "最近流行ってるらしいから流行りに乗ってるみたいでなんだか恥ずかしいんだけどね。"
        },
        {
            "st": 1095.4099999999999,
            "et": 1097.89,
            "text": "ジョギングすると体力ってつくもんなんですか?"
        },
        { "st": 1098.49, "et": 1099.75, "text": "うーん、そうね。" },
        {
            "st": 1100.49,
            "et": 1103.07,
            "text": "前に比べたら疲れにくくなったかな。"
        },
        {
            "st": 1103.9499999999998,
            "et": 1105.71,
            "text": "それによく眠れるよ。"
        },
        { "st": 1105.9099999999999, "et": 1106.67, "text": "そうですか。" },
        { "st": 1107.45, "et": 1107.97, "text": "いいですね。" },
        { "st": 1108.4699999999998, "et": 1108.85, "text": "うん。" },
        {
            "st": 1109.25,
            "et": 1113.41,
            "text": "それにね、実は何より気持ちの面でもすごくいいんだ。"
        },
        { "st": 1114.23, "et": 1115.09, "text": "なんていうか、" },
        {
            "st": 1115.81,
            "et": 1119.39,
            "text": "例えば嫌なことがあっても落ち込みにくくなったり。"
        },
        { "st": 1119.57, "et": 1120.35, "text": "へー。" },
        {
            "st": 1120.67,
            "et": 1127.51,
            "text": "だからね、どっちかっていうと心の健康のためにしばらく続けてみようと思ってるんだ。"
        },
        {
            "st": 1133.7099999999998,
            "et": 1139.7500000000005,
            "text": "女の人はジョギングを始めて一番良かったことは何だと言っていますか?"
        },
        {
            "st": 1142.83,
            "et": 1145.01,
            "text": "ここでちょっと休みましょう。"
        },
        { "st": 1177.71, "et": 1180.07, "text": "ではまた続けます。" },
        {
            "st": 1185.7699999999998,
            "et": 1192.23,
            "text": "問題3問題3では問題用紙に何も印刷されていません。"
        },
        {
            "st": 1193.75,
            "et": 1198.65,
            "text": "この問題は全体としてどんな内容かを聞く問題です。"
        },
        { "st": 1200.45, "et": 1202.51, "text": "話の前に質問はありません。" },
        { "st": 1203.65, "et": 1205.49, "text": "まず話を聞いてください。" },
        {
            "st": 1206.99,
            "et": 1209.71,
            "text": "それから質問と選択肢を聞いて、"
        },
        {
            "st": 1210.39,
            "et": 1215.01,
            "text": "1から4の中から最も良いものを1つ選んでください。"
        },
        { "st": 1217.79, "et": 1219.81, "text": "では始めます。" },
        {
            "st": 1228.24,
            "et": 1232.94,
            "text": "1番大学の先生が授業で話しています。"
        },
        {
            "st": 1235.1,
            "et": 1240.06,
            "text": "先日リンゴ農家の方に頼まれて講演会で話してきました。"
        },
        {
            "st": 1241.34,
            "et": 1246.18,
            "text": "今リンゴ農家ではネズミによる被害が問題になっています。"
        },
        {
            "st": 1247.34,
            "et": 1253.52,
            "text": "ネズミがリンゴの木をかじってひどい時には木が死んでしまうこともあるんですね。"
        },
        {
            "st": 1254.82,
            "et": 1260.24,
            "text": "良いリンゴを作るためにはネズミの行動を知らないと対策が立てられません。"
        },
        {
            "st": 1261.44,
            "et": 1266.38,
            "text": "そこでネズミの研究をしている私が講演をしたというわけです。"
        },
        { "st": 1272.36, "et": 1274.98, "text": "講演のテーマは何でしたか?" },
        {
            "st": 1276.7600000000002,
            "et": 1279.96,
            "text": "1.ネズミの行動について"
        },
        { "st": 1282.72, "et": 1286.12, "text": "2.ネズミの種類について" },
        { "st": 1288.72, "et": 1291.92, "text": "3.リンゴの被害について" },
        { "st": 1294.82, "et": 1298.4, "text": "4.リンゴの育て方について" },
        {
            "st": 1309.76,
            "et": 1314.08,
            "text": "2番 留守番電話のメッセージを聞いています。"
        },
        {
            "st": 1318.9699999999998,
            "et": 1320.49,
            "text": "東旅行の田中です。"
        },
        {
            "st": 1321.19,
            "et": 1325.83,
            "text": "あのお問い合わせいただきました韓国行きの件でご連絡いたします。"
        },
        {
            "st": 1327.01,
            "et": 1334.77,
            "text": "ご希望の飛行機はあいにく席がいっぱいでしてキャンセル待ちか次の便への変更が必要となります。"
        },
        {
            "st": 1336.15,
            "et": 1341.53,
            "text": "次の便でも午後4時には到着しますのでセミナーには間に合うかと思います。"
        },
        {
            "st": 1342.55,
            "et": 1344.89,
            "text": "こちらはまだ空席がございます。"
        },
        {
            "st": 1347.07,
            "et": 1352.91,
            "text": "私は午後8時頃までは店におりますのでご連絡いただけますでしょうか。"
        },
        {
            "st": 1354.17,
            "et": 1359.53,
            "text": "またホテルのご予約なども受けたまわっておりますのでよろしくお願いします。"
        },
        {
            "st": 1368.83,
            "et": 1370.89,
            "text": "何についてのメッセージですか。"
        },
        { "st": 1372.87, "et": 1375.59, "text": "1.飛行機の予約" },
        { "st": 1378.57, "et": 1381.67, "text": "2.旅行会社の営業時間" },
        { "st": 1384.72, "et": 1387.52, "text": "3.セミナーの日程" },
        {
            "st": 1390.56,
            "et": 1393.2800000000002,
            "text": "4.ホテルのキャンセル"
        },
        {
            "st": 1405.1000000000001,
            "et": 1409.34,
            "text": "3番 テレビでアナウンサーが話しています。"
        },
        {
            "st": 1411.48,
            "et": 1414.52,
            "text": "今日は山田美智子さんをゲストにお迎えしました。"
        },
        {
            "st": 1415.74,
            "et": 1420.24,
            "text": "山田さんはお子さんが生まれたのをきっかけに専業主婦となられました。"
        },
        {
            "st": 1421.3999999999999,
            "et": 1426.38,
            "text": "そのため家庭の収入が減り自然と節約するようになったそうです。"
        },
        {
            "st": 1427.6000000000001,
            "et": 1433.1,
            "text": "今では色々と工夫するのが楽しくすっかり節約が趣味になっているとのことです。"
        },
        {
            "st": 1434.3,
            "et": 1443.52,
            "text": "今日はその中から毎日の生活の中ですぐ実践できることを紹介していただきますのでどうぞメモを用意してご覧ください。"
        },
        { "st": 1449.62, "et": 1451.86, "text": "この番組のテーマは何ですか?" },
        { "st": 1453.78, "et": 1457.1, "text": "1.仕事を続ける工夫" },
        { "st": 1460.08, "et": 1463.16, "text": "2.収入を増やす工夫" },
        {
            "st": 1466.2199999999998,
            "et": 1469.6,
            "text": "3.お金を節約する工夫"
        },
        { "st": 1472.54, "et": 1476.44, "text": "4.家事の時間を節約する工夫" },
        {
            "st": 1488.1,
            "et": 1492.62,
            "text": "4番 大学のサークルのリーダーが話しています。"
        },
        {
            "st": 1494.72,
            "et": 1498.48,
            "text": "土曜日は小学生との交流会お疲れ様でした。"
        },
        {
            "st": 1499.7199999999998,
            "et": 1503.28,
            "text": "子供たちはみんなとても楽しんでくれていましたよね。"
        },
        {
            "st": 1504.86,
            "et": 1509.92,
            "text": "先生方や保護者の方も高く評価してくださったようでよかったです。"
        },
        {
            "st": 1511.1200000000001,
            "et": 1514.04,
            "text": "ただ場所に問題があったように思います。"
        },
        {
            "st": 1515.38,
            "et": 1519.76,
            "text": "最初は広くて動きやすくていいなと思っていたんですが、"
        },
        {
            "st": 1520.3000000000002,
            "et": 1523.92,
            "text": "逆に広すぎて子供たちと距離がありました。"
        },
        {
            "st": 1525.5399999999997,
            "et": 1528.28,
            "text": "次回、来月のクリスマスパーティーでは、"
        },
        { "st": 1528.82, "et": 1529.96, "text": "内容だけじゃなく、" },
        {
            "st": 1530.6,
            "et": 1533.48,
            "text": "このような点についても気をつけたいと思います。"
        },
        {
            "st": 1535.1,
            "et": 1539.76,
            "text": "えー、皆さんは何か気づいた点はありませんか?"
        },
        {
            "st": 1545.8599999999997,
            "et": 1549.28,
            "text": "リーダーの話の主な内容は何ですか?"
        },
        {
            "st": 1551.3600000000001,
            "et": 1555.26,
            "text": "1.小学生との交流会の内容"
        },
        {
            "st": 1558.2999999999997,
            "et": 1562.38,
            "text": "2.小学生との交流会の反省点"
        },
        {
            "st": 1565.32,
            "et": 1568.82,
            "text": "3.クリスマスパーティーの内容"
        },
        {
            "st": 1571.82,
            "et": 1575.46,
            "text": "4.クリスマスパーティーの反省点"
        },
        {
            "st": 1587.46,
            "et": 1591.817,
            "text": "5番 男の人と女の人が話しています。"
        },
        {
            "st": 1593.899,
            "et": 1598.297,
            "text": "転職して、一ヶ月だったんだよね。どう？新しい会社は？"
        },
        {
            "st": 1598.65,
            "et": 1601.332,
            "text": "うん、最近やっと慣れてきたかな。"
        },
        {
            "st": 1602.069,
            "et": 1603.706,
            "text": "覚えることがたくさんあって、結構、夜も遅いんだ。"
        },
        { "st": 1606.122, "et": 1606.725, "text": "そうなんだ。" },
        {
            "st": 1607.323,
            "et": 1611.229,
            "text": "うん。前の会社はあまりいそがしくなかったから、"
        },
        {
            "st": 1611.599,
            "et": 1616.884,
            "text": "その点はよかったけど、単調だし、誰でもできる仕事だったからねえ。"
        },
        {
            "st": 1618.015,
            "et": 1620.675,
            "text": "今は責任ある仕事をさせてもらえるから、"
        },
        { "st": 1621, "et": 1622.708, "text": "それが、一番の魅力かな。" },
        { "st": 1623.677, "et": 1625.8, "text": "毎日大変だけど、楽しいよ。" },
        {
            "st": 1631.834,
            "et": 1636.687,
            "text": "女の人は新しい仕事についてどう思っていますか?"
        },
        { "st": 1638.5499999999997, "et": 1642.07, "text": "1.簡単で楽しい" },
        { "st": 1644.7499999999998, "et": 1648.65, "text": "2.忙しいが面白い" },
        {
            "st": 1651.2199999999998,
            "et": 1654.68,
            "text": "3.単調でつまらない"
        },
        {
            "st": 1657.4599999999998,
            "et": 1675.02,
            "text": "4.仕事は多いが簡単だ問題4問題4では問題用紙に何も印刷されていません。"
        },
        { "st": 1676.22, "et": 1678.22, "text": "まず文を聞いてください。" },
        {
            "st": 1679.78,
            "et": 1682.74,
            "text": "それからそれに対する返事を聞いて、"
        },
        {
            "st": 1683.2800000000002,
            "et": 1688.12,
            "text": "1から3の中から最も良いものを1つ選んでください。"
        },
        { "st": 1691.2800000000002, "et": 1693.12, "text": "では始めます。" },
        {
            "st": 1701.7,
            "et": 1707.02,
            "text": "1番 あ、台所の電球切れちゃったよ。"
        },
        { "st": 1708.88, "et": 1712.36, "text": "1.あ、電気もう消すね。" },
        {
            "st": 1714.34,
            "et": 1717.9,
            "text": "2.え、新しいのを買ってこなきゃ。"
        },
        {
            "st": 1719.98,
            "et": 1723.74,
            "text": "3.うん、台所きれいにしてね。"
        },
        {
            "st": 1735.3899999999999,
            "et": 1739.65,
            "text": "2番 いらっしゃいませ。何かお探しですか?"
        },
        {
            "st": 1741.6499999999999,
            "et": 1745.59,
            "text": "1.あ、ちょっと見てるだけです。"
        },
        {
            "st": 1746.9699999999998,
            "et": 1750.25,
            "text": "2.いいえ、さっき来たばかりです。"
        },
        {
            "st": 1752.1299999999999,
            "et": 1755.49,
            "text": "3.はい、何でも結構です。"
        },
        {
            "st": 1767.1599999999999,
            "et": 1773.76,
            "text": "3番 やるだけのことはやったし、あとは合格発表の日を待つだけだね。"
        },
        { "st": 1775.76, "et": 1778.52, "text": "1.本当に悔しいね。" },
        {
            "st": 1780.6999999999998,
            "et": 1783.48,
            "text": "2.もう少し頑張るしかないか。"
        },
        { "st": 1785.74, "et": 1788.4, "text": "3.今度こそ受かりたいよね。" },
        {
            "st": 1800.5800000000002,
            "et": 1804.12,
            "text": "4番 あの、お茶でもいかがですか?"
        },
        { "st": 1806.28, "et": 1808.96, "text": "1.お世話になっております。" },
        {
            "st": 1810.8999999999999,
            "et": 1814.22,
            "text": "2.はい、大変美味しかったです。"
        },
        {
            "st": 1816.26,
            "et": 1819.48,
            "text": "3.すみません、どうぞお構いなく。"
        },
        {
            "st": 1831.41,
            "et": 1837.97,
            "text": "5番 ねえ、山田さん。参加できないのなら、もう少し早く教えてくれなくちゃ"
        },
        {
            "st": 1840.15,
            "et": 1843.31,
            "text": "1.え、連絡が必要だったんだ。"
        },
        {
            "st": 1845.33,
            "et": 1849.79,
            "text": "2.そう、今度は教えてもらえるといいね。"
        },
        {
            "st": 1851.71,
            "et": 1854.97,
            "text": "3.少しでも早く参加したかったんだ。"
        },
        {
            "st": 1866.8600000000001,
            "et": 1873.3,
            "text": "6番 確か、明日中学の時のクラス会だったよね。行くんでしょう?"
        },
        { "st": 1875.38, "et": 1877.82, "text": "1.楽しみにしてるんだ。" },
        {
            "st": 1879.9599999999998,
            "et": 1882.52,
            "text": "2.楽しんできてね。"
        },
        { "st": 1884.1999999999998, "et": 1886.48, "text": "3.楽しいでしょ?" },
        {
            "st": 1898.0299999999997,
            "et": 1902.61,
            "text": "7番 昨日、また電気つけっぱなしで寝てたね。"
        },
        {
            "st": 1904.81,
            "et": 1908.13,
            "text": "1つけといてくれたんだね。ありがとう。"
        },
        {
            "st": 1910.3899999999999,
            "et": 1913.65,
            "text": "2.だって、暗いほうが好きだから。"
        },
        {
            "st": 1915.79,
            "et": 1920.07,
            "text": "3.ごめん、本読んでて寝ちゃったみたい。"
        },
        {
            "st": 1931.86,
            "et": 1937.5,
            "text": "8番 さっき言ってた本、今度貸してもらえると嬉しいんだけど。"
        },
        { "st": 1939.6, "et": 1942.5, "text": "1.こっちこそ助かったよ。" },
        {
            "st": 1944.4399999999998,
            "et": 1947.68,
            "text": "2.うん、忘れないようにするね。"
        },
        { "st": 1949.7, "et": 1952.68, "text": "3.じゃあ悪いけどお願いね。" },
        {
            "st": 1964.28,
            "et": 1970.64,
            "text": "9番 あの、こちらで山田課長とお会いする約束なんですが。"
        },
        {
            "st": 1972.32,
            "et": 1975.44,
            "text": "1.お会いできてよかったです。"
        },
        {
            "st": 1977.12,
            "et": 1980.38,
            "text": "2.はい、少々お待ちください。"
        },
        {
            "st": 1982.3799999999999,
            "et": 1985.72,
            "text": "3.確かにお約束いたします。"
        },
        {
            "st": 1997.58,
            "et": 2003.18,
            "text": "10番 ああ、田中さんのご主人ですか。初めまして。"
        },
        {
            "st": 2005.26,
            "et": 2008.02,
            "text": "1.大変ご無沙汰しております。"
        },
        { "st": 2010.12, "et": 2013.32, "text": "2.はい、相変わらずです。" },
        {
            "st": 2015.18,
            "et": 2018.1,
            "text": "3.妻がお世話になっております。"
        },
        {
            "st": 2030.01,
            "et": 2035.89,
            "text": "11番 昨日ね、この角で自転車にぶつかりそうになっちゃったんだ。ああ。"
        },
        {
            "st": 2037.8899999999999,
            "et": 2040.71,
            "text": "1.危ないんだよね、ここ。"
        },
        { "st": 2042.87, "et": 2045.99, "text": "2.えー、痛かったでしょう。" },
        { "st": 2048.19, "et": 2050.97, "text": "3.ここは問題ないよ。" },
        {
            "st": 2062.64,
            "et": 2067.28,
            "text": "12番 君、なんてことをしてくれたんだ。"
        },
        {
            "st": 2069.5199999999995,
            "et": 2072.5,
            "text": "1.いえ、とんでもないです。"
        },
        { "st": 2074.5399999999995, "et": 2076.8, "text": "2.恐縮です。" },
        { "st": 2078.64, "et": 2081.38, "text": "3.申し訳ございません。" },
        {
            "st": 2086.98,
            "et": 2091.84,
            "text": "問題5 問題5では長めの話を聞きます。"
        },
        {
            "st": 2093.54,
            "et": 2096.66,
            "text": "問題用紙にメモをとってもかまいません。"
        },
        {
            "st": 2099.24,
            "et": 2105,
            "text": "1番、2番問題用紙に何も印刷されていません。"
        },
        { "st": 2106.14, "et": 2108.18, "text": "まず話を聞いてください。" },
        {
            "st": 2109.92,
            "et": 2112.7,
            "text": "それから質問と選択肢を聞いて、"
        },
        {
            "st": 2113.2400000000002,
            "et": 2117.86,
            "text": "1から4の中から最も良いものを1つ選んでください。"
        },
        { "st": 2120.88, "et": 2122.22, "text": "では始めます。" },
        {
            "st": 2129.51,
            "et": 2137.67,
            "text": "1番 図書館で女の人が係員と貸し出し用CDについて話しています。"
        },
        { "st": 2139.27, "et": 2139.79, "text": "すいません。" },
        {
            "st": 2140.55,
            "et": 2143.73,
            "text": "子供が好きそうな歌のCDを探してるんですけど、"
        },
        {
            "st": 2144.73,
            "et": 2147.91,
            "text": "この4月に小学校に入ったばかりの子なんですが。"
        },
        {
            "st": 2148.81,
            "et": 2153.03,
            "text": "えーと、こちらが子供向けのCDコーナーです。"
        },
        {
            "st": 2154.2499999999995,
            "et": 2157.77,
            "text": "みんなで歌おうっていうCDが人気があるんですが。"
        },
        { "st": 2158.75, "et": 2160.37, "text": "えーと、あー、" },
        {
            "st": 2161.17,
            "et": 2164.81,
            "text": "あいにくみんなで歌おうは今貸し出し中ですね。"
        },
        { "st": 2165.33, "et": 2166.01, "text": "そうですか。" },
        {
            "st": 2166.65,
            "et": 2172.03,
            "text": "えーと、それからこちらの懐かしい子供の歌は、"
        },
        {
            "st": 2172.65,
            "et": 2175.79,
            "text": "昔懐かしい小さいお子さん向けの歌ですね。"
        },
        {
            "st": 2176.91,
            "et": 2183.93,
            "text": "それと、こちらのアニメの歌はテレビの人気アニメの歌を集めたものです。"
        },
        {
            "st": 2184.37,
            "et": 2186.63,
            "text": "へー、いろいろあるんですね。"
        },
        {
            "st": 2187.73,
            "et": 2193.35,
            "text": "息子にはアニメより私が子供の頃歌ったような歌を聞かせたいですね。"
        },
        {
            "st": 2194.03,
            "et": 2199.05,
            "text": "あー、あといろんな国の子供の歌を集めたCDもありますよ。"
        },
        {
            "st": 2200.15,
            "et": 2202.41,
            "text": "世界の子供の歌って言うんですが、"
        },
        { "st": 2202.9500000000003, "et": 2203.59, "text": "こちらです。" },
        {
            "st": 2203.99,
            "et": 2207.79,
            "text": "あー、でもこれ外国語なんですね。"
        },
        { "st": 2208.79, "et": 2210.57, "text": "やっぱりさっきのにします。" },
        {
            "st": 2216.5099999999998,
            "et": 2220.33,
            "text": "女の人は今日、どのCDを借りますか?"
        },
        { "st": 2222.2499999999995, "et": 2225.39, "text": "1.みんなで歌おう" },
        { "st": 2227.93, "et": 2230.85, "text": "2.懐かしい子供の歌" },
        { "st": 2233.97, "et": 2236.31, "text": "3.アニメの歌" },
        { "st": 2239.330000000001, "et": 2242.37, "text": "4.世界の子供の歌" },
        {
            "st": 2254.06,
            "et": 2259.82,
            "text": "2番。親子3人が遊園地へ行く計画を立てています。"
        },
        {
            "st": 2261.8199999999997,
            "et": 2264.86,
            "text": "今日、遊園地の無料チケットをもらったのよ。"
        },
        { "st": 2265.06, "et": 2267.66, "text": "お、遊園地か。いいね。" },
        {
            "st": 2268.52,
            "et": 2271.12,
            "text": "じゃあ、今度の日曜日に3人で行こうか。"
        },
        { "st": 2271.6, "et": 2273.26, "text": "休日だと混むだろうから、" },
        {
            "st": 2273.74,
            "et": 2275.78,
            "text": "早い時間に行ったほうがいいかもね。"
        },
        {
            "st": 2276.32,
            "et": 2280.62,
            "text": "ねえねえ、僕、来週の月曜日、学校お休みだよ。"
        },
        { "st": 2280.9, "et": 2282.66, "text": "あら、そうだったわね。" },
        {
            "st": 2283.64,
            "et": 2287.18,
            "text": "月曜日なら平日だし、空いてそうね。"
        },
        { "st": 2288.06, "et": 2290.28, "text": "ねえ、仕事を休めないの?" },
        {
            "st": 2290.48,
            "et": 2294.9,
            "text": "うーん、今ちょっと忙しいから難しいなあ。"
        },
        {
            "st": 2295.06,
            "et": 2299.82,
            "text": "でも、休みの日は乗り物に乗るのにもすごく待たされるって言ってたよ。"
        },
        {
            "st": 2300.54,
            "et": 2303.3,
            "text": "空いてる日のほうがたくさん遊べていいよ。"
        },
        { "st": 2304, "et": 2307.02, "text": "そうよね。仕方ない。" },
        {
            "st": 2307.6,
            "et": 2309.9,
            "text": "じゃあ、お母さんと2人で行こうか。"
        },
        {
            "st": 2310.78,
            "et": 2315.1,
            "text": "お父さん抜きで、空いてる遊園地で思いっきり楽しんじゃおう。"
        },
        {
            "st": 2315.2,
            "et": 2319.78,
            "text": "おいおい、そんな。うーん、わかった。"
        },
        {
            "st": 2320.58,
            "et": 2322.52,
            "text": "なんとか休みを取らせてもらうよ。"
        },
        { "st": 2322.64, "et": 2323.7000000000003, "text": "やったー!" },
        {
            "st": 2329.6799999999994,
            "et": 2333.28,
            "text": "遊園地へはいつ、何人で行きますか?"
        },
        {
            "st": 2335.2400000000007,
            "et": 2338.94,
            "text": "1.休日に3人で行く。"
        },
        {
            "st": 2341.5399999999995,
            "et": 2344.48,
            "text": "2.休日に2人で行く。"
        },
        { "st": 2347.5, "et": 2351.48, "text": "3. 平日に3人で行く。" },
        {
            "st": 2353.8799999999997,
            "et": 2357.34,
            "text": "4. 平日に2人で行く。"
        },
        { "st": 2364.47, "et": 2366.47, "text": "まず話を聞いてください。" },
        { "st": 2367.99, "et": 2370.49, "text": "それから2つの質問を聞いて、" },
        {
            "st": 2371.23,
            "et": 2377.65,
            "text": "それぞれ問題用紙の1から4の中から最も良いものを1つ選んでください。"
        },
        { "st": 2380.71, "et": 2382.09, "text": "では始めます。" },
        { "st": 2390.47, "et": 2391.31, "text": "3番。" },
        {
            "st": 2392.23,
            "et": 2397.97,
            "text": "男の人と女の人が明日の旅行コースの説明を聞いています。"
        },
        {
            "st": 2399.99,
            "et": 2403.63,
            "text": "えー、明日は皆様にお選びいただけるよう、"
        },
        { "st": 2404.33, "et": 2406.15, "text": "コースを4つご用意しました。" },
        {
            "st": 2407.27,
            "et": 2409.33,
            "text": "それぞれ半日のコースなので、"
        },
        { "st": 2410.05, "et": 2412.03, "text": "午前に1つ、午後に1つ、" },
        {
            "st": 2412.67,
            "et": 2416.99,
            "text": "1日に2つのコースを自由に組み合わせてご参加いただけます。"
        },
        { "st": 2418.01, "et": 2419.59, "text": "まずリラックスコース。" },
        {
            "st": 2420.39,
            "et": 2423.53,
            "text": "こちらは温泉をのんびり楽しむコースです。"
        },
        {
            "st": 2424.53,
            "et": 2427.19,
            "text": "ワクワクコースは畑での収穫、"
        },
        {
            "st": 2427.85,
            "et": 2431.65,
            "text": "牧場での動物との触れ合いを体験いただくコースです。"
        },
        { "st": 2433.05, "et": 2434.03, "text": "ロマンコースでは、" },
        {
            "st": 2434.75,
            "et": 2437.33,
            "text": "ドラマでも話題になりましたお城を訪ね、"
        },
        {
            "st": 2438.03,
            "et": 2440.05,
            "text": "歴史を肌で感じていただきます。"
        },
        { "st": 2441.07, "et": 2442.81, "text": "最後に欲張りコース。" },
        {
            "st": 2443.73,
            "et": 2447.71,
            "text": "このコースでは地元名産の蕎麦を味わっていただいた後、"
        },
        {
            "st": 2448.3700000000003,
            "et": 2451.93,
            "text": "大型ショッピングセンターでお買い物もしていただけます。"
        },
        { "st": 2453.31, "et": 2454.17, "text": "どれにしようか。" },
        {
            "st": 2454.97,
            "et": 2458.07,
            "text": "2人で1つずつ好きなの選んで一緒に回ろうか。"
        },
        { "st": 2458.53, "et": 2459.11, "text": "そうね。" },
        { "st": 2460.07, "et": 2461.73, "text": "あなたはやっぱり温泉?" },
        {
            "st": 2462.43,
            "et": 2464.51,
            "text": "うーん、そのつもりだったんだけど、"
        },
        { "st": 2465.23, "et": 2466.71, "text": "さっきの説明聞いてたら、" },
        {
            "st": 2467.15,
            "et": 2469.29,
            "text": "いろいろ体験してみるのも悪くないかなって。"
        },
        {
            "st": 2470.15,
            "et": 2472.87,
            "text": "今ってなかなか自然を感じるチャンスもないし。"
        },
        { "st": 2473.39, "et": 2474.03, "text": "いいわね。" },
        {
            "st": 2475.1699999999996,
            "et": 2476.93,
            "text": "でも蕎麦はいいの?"
        },
        { "st": 2477.41, "et": 2478.81, "text": "蕎麦も捨てがたいけど、" },
        { "st": 2479.25, "et": 2480.89, "text": "今回はやっぱり体験かな。" },
        { "st": 2481.63, "et": 2484.09, "text": "そう、じゃあ1つはそれね。" },
        {
            "st": 2484.9300000000003,
            "et": 2488.67,
            "text": "私はドラマで見てからここのお城気になってて、"
        },
        { "st": 2489.17, "et": 2490.45, "text": "一度見てみたかったんだ。" },
        {
            "st": 2491.13,
            "et": 2492.93,
            "text": "じゃあ今回はそれでいこうか。"
        },
        {
            "st": 2498.87,
            "et": 2506.01,
            "text": "質問1男の人はどのコースを選びましたか?"
        },
        {
            "st": 2520.2999999999997,
            "et": 2525.7,
            "text": "質問2女の人はどのコースを選びましたか?"
        }
    ]
}
